xsettings/__init__.py
xsettings/default_converters.py
xsettings/env_settings.py
xsettings/errors.py
xsettings/fields.py
xsettings/retreivers.py
xsettings/settings.py
xsettings-1.4.0.dist-info/LICENSE
xsettings-1.4.0.dist-info/METADATA
xsettings-1.4.0.dist-info/WHEEL
xsettings-1.4.0.dist-info/RECORD
