Metadata-Version: 2.1
Name: xsettings
Version: 1.4.0
Summary: Ways to document, centeralize, retreive and validate settings.
Home-page: https://github.com/xyngular/py-xsettings
Keywords: settings,lazy,configuration
Author: Josh Orr
Author-email: josh@orr.blue
Requires-Python: >=3.8,<4.0
Classifier: License :: OSI Approved :: The Unlicense (Unlicense)
Classifier: Programming Language :: Python :: 3
Classifier: Programming Language :: Python :: 3.8
Classifier: Programming Language :: Python :: 3.9
Classifier: Programming Language :: Python :: 3.10
Classifier: Programming Language :: Python :: 3.11
Classifier: Topic :: Software Development :: Libraries :: Python Modules
Requires-Dist: ciso8601 (>=2.3.0,<3.0.0)
Requires-Dist: xbool (>=1.0.0,<2.0.0)
Requires-Dist: xinject (>=1.2.0,<2.0.0)
Requires-Dist: xloop (>=1.0.1,<2.0.0)
Requires-Dist: xsentinels (>=1.2.0,<2.0.0)
Project-URL: Repository, https://github.com/xyngular/py-xsettings
